pyCryptoTransactions/Coin.py
pyCryptoTransactions/Currency.py
pyCryptoTransactions/Importer.py
pyCryptoTransactions/Transaction.py
pyCryptoTransactions/Wallet.py
pyCryptoTransactions/__init__.py
pyCryptoTransactions/exchanges/__init__.py
pyCryptoTransactions/exchanges/binance/binanceManual.py
pyCryptoTransactions/exchanges/coinbase/__init__.py
pyCryptoTransactions/exchanges/coinbase/coinbase.py
pyCryptoTransactions/exchanges/coinbase/coinbaseApiWrapper/.git
pyCryptoTransactions/exchanges/coinbase/coinbaseApiWrapper/.gitignore
pyCryptoTransactions/exchanges/coinbase/coinbaseApiWrapper/README.md
pyCryptoTransactions/exchanges/coinbase/coinbaseApiWrapper/coinbase/CoinbaseAPIKeyAuthentication.py
pyCryptoTransactions/exchanges/coinbase/coinbaseApiWrapper/coinbase/CoinbaseAuthentication.py
pyCryptoTransactions/exchanges/coinbase/coinbaseApiWrapper/coinbase/CoinbaseOAuth.py
pyCryptoTransactions/exchanges/coinbase/coinbaseApiWrapper/coinbase/CoinbaseOAuthAuthentication.py
pyCryptoTransactions/exchanges/coinbase/coinbaseApiWrapper/coinbase/CoinbaseRPC.py
pyCryptoTransactions/exchanges/coinbase/coinbaseApiWrapper/coinbase/__init__.py
pyCryptoTransactions/exchanges/coinbase/coinbaseApiWrapper/coinbase/error.py
pyCryptoTransactions/exporters/accointing.py
pyCryptoTransactions/exporters/default.py
pyCryptoTransactions/exporters/koinly.py
pyCryptoTransactions/manual/CSVImporter.py
pyCryptoTransactions/manual/StakeTaxImporter.py
pyCryptoTransactions/networks/Network.py
pyCryptoTransactions/networks/__init__.py
pyCryptoTransactions/networks/binanceChain/binanceChain.py
pyCryptoTransactions/networks/bitcoin/Archive/generateBitcoinAdresses.py
pyCryptoTransactions/networks/bitcoin/Archive/prepend_bytes.py
pyCryptoTransactions/networks/bitcoin/BitcoinImport.py
pyCryptoTransactions/networks/bitcoin/Network_.py
pyCryptoTransactions/networks/bitcoin/__init__.py
pyCryptoTransactions/networks/bitcoin/decodeXpub.py
pyCryptoTransactions/networks/bitcoin/pyCoinTest.py
pycryptotransactions-0.1.3.dist-info/WHEEL
pycryptotransactions-0.1.3.dist-info/METADATA
pycryptotransactions-0.1.3.dist-info/RECORD
